putiopy.py
putio_py-8.8.0.dist-info/METADATA
putio_py-8.8.0.dist-info/WHEEL
putio_py-8.8.0.dist-info/top_level.txt
putio_py-8.8.0.dist-info/RECORD
