Metadata-Version: 2.2
Name: putio.py
Version: 8.8.0
Summary: Python client for put.io API v2
Author-email: Cenk Altı <cenkalti@gmail.com>
License: MIT
Project-URL: Homepage, https://github.com/cenkalti/putio.py
Project-URL: Issues, https://github.com/cenkalti/putio.py/issues
Requires-Python: >=3.9
Requires-Dist: requests
Requires-Dist: tus.py
